ITagSDK/__init__.py
ITagSDK/demo.py
ITagSDK/alpha_data_sdk/__init__.py
ITagSDK/alpha_data_sdk/alpha_data_sdk.py
ITagSDK/alpha_data_sdk/models.py
ITagSDK/openitag_sdk/__init__.py
ITagSDK/openitag_sdk/itag_sdk.py
alibaba_itag_sdk-0.0.1.dist-info/METADATA
alibaba_itag_sdk-0.0.1.dist-info/WHEEL
alibaba_itag_sdk-0.0.1.dist-info/top_level.txt
alibaba_itag_sdk-0.0.1.dist-info/RECORD
