Metadata-Version: 2.1
Name: alibaba-itag-sdk
Version: 0.0.1
Summary: iTAG内部用的SDK
Home-page: 
Author: ZhangMr
Author-email: 2864640437@qq.com
License: MIT
Classifier: License :: OSI Approved :: MIT License
Classifier: Programming Language :: Python
Classifier: Programming Language :: Python :: 3
Classifier: Programming Language :: Python :: 3.6
Classifier: Programming Language :: Python :: Implementation :: CPython
Classifier: Programming Language :: Python :: Implementation :: PyPy
Requires-Python: >=3.6.0
Requires-Dist: aiohttp (==3.8.4)
Requires-Dist: aiosignal (==1.3.1)
Requires-Dist: alibabacloud-credentials (==0.3.1)
Requires-Dist: alibabacloud-darabonba-array (==0.1.0)
Requires-Dist: alibabacloud-darabonba-number (==0.0.4)
Requires-Dist: alibabacloud-darabonba-string (==0.0.4)
Requires-Dist: alibabacloud-endpoint-util (==0.0.3)
Requires-Dist: alibabacloud-gateway-spi (==0.0.1)
Requires-Dist: alibabacloud-openapi-util (==0.2.1)
Requires-Dist: alibabacloud-openitag20220616 (==1.0.1)
Requires-Dist: alibabacloud-tea (==0.2.9)
Requires-Dist: alibabacloud-tea-fileform (==0.0.5)
Requires-Dist: alibabacloud-tea-openapi (==0.3.6)
Requires-Dist: alibabacloud-tea-util (==0.3.8)
Requires-Dist: alibabacloud-tea-xml (==0.0.2)
Requires-Dist: async-timeout (==4.0.2)
Requires-Dist: attrs (==22.2.0)
Requires-Dist: certifi (==2022.12.7)
Requires-Dist: cffi (==1.15.1)
Requires-Dist: charset-normalizer (==2.1.1)
Requires-Dist: cryptography (==39.0.1)
Requires-Dist: darabonba-rsa (==0.0.7)
Requires-Dist: frozenlist (==1.3.3)
Requires-Dist: idna (==3.4)
Requires-Dist: multidict (==6.0.4)
Requires-Dist: pyasn1 (==0.4.8)
Requires-Dist: pycparser (==2.21)
Requires-Dist: pycryptodome (==3.17)
Requires-Dist: requests (==2.28.1)
Requires-Dist: requests-toolbelt (==0.10.1)
Requires-Dist: rsa (==4.9)
Requires-Dist: urllib3 (==1.26.14)
Requires-Dist: yarl (==1.8.2)
